[
  {
      "featureType": "all",
      "elementType": "labels",
      "stylers": [
          {
              "visibility": "off"
          }
      ]
  },
  {
      "featureType": "all",
      "elementType": "labels.icon",
      "stylers": [
          {
              "visibility": "off"
          }
      ]
  },
  {
      "featureType": "administrative",
      "elementType": "labels.text.fill",
      "stylers": [
          {
              "color": "#444444"
          }
      ]
  },
  {
      "featureType": "administrative",
      "elementType": "labels.icon",
      "stylers": [
          {
              "visibility": "off"
          }
      ]
  },
  {
      "featureType": "landscape",
      "elementType": "all",
      "stylers": [
          {
              "color": "#f2f2f2"
          }
      ]
  },
  {
      "featureType": "landscape",
      "elementType": "labels.icon",
      "stylers": [
          {
              "visibility": "off"
          }
      ]
  },
  {
      "featureType": "poi",
      "elementType": "all",
      "stylers": [
          {
              "visibility": "off"
          }
      ]
  },
  {
      "featureType": "road",
      "elementType": "all",
      "stylers": [
          {
              "color": "#551155"
          }
      ]
  },
  {
      "featureType": "road",
      "elementType": "labels.icon",
      "stylers": [
          {
              "visibility": "off"
          }
      ]
  },
  {
      "featureType": "road.highway",
      "elementType": "all",
      "stylers": [
          {
              "visibility": "simplified"
          }
      ]
  },
  {
      "featureType": "road.highway",
      "elementType": "labels.icon",
      "stylers": [
          {
              "visibility": "off"
          }
      ]
  },
  {
      "featureType": "road.arterial",
      "elementType": "labels.icon",
      "stylers": [
          {
              "visibility": "off"
          }
      ]
  },
  {
      "featureType": "road.local",
      "elementType": "all",
      "stylers": [
          {
              "color": "#551155"
          }
      ]
  },
  {
      "featureType": "road.local",
      "elementType": "labels.icon",
      "stylers": [
          {
              "visibility": "off"
          }
      ]
  },
  {
      "featureType": "transit",
      "elementType": "all",
      "stylers": [
          {
              "visibility": "on"
          },
          {
              "color": "#551155"
          }
      ]
  },
  {
      "featureType": "transit",
      "elementType": "labels.icon",
      "stylers": [
          {
              "visibility": "off"
          }
      ]
  },
  {
      "featureType": "transit.line",
      "elementType": "labels.icon",
      "stylers": [
          {
              "visibility": "off"
          }
      ]
  },
  {
      "featureType": "water",
      "elementType": "all",
      "stylers": [
          {
              "color": "#551155"
          },
          {
              "visibility": "on"
          }
      ]
  }
]